json_memoize/__init__.py
json_memoize/json_memoize.py
json_memoize/scratch 2.py
json_memoize/scratch.py
json_memoize/scratch_3.py
json_memoize-1.1.0.dist-info/LICENSE
json_memoize-1.1.0.dist-info/METADATA
json_memoize-1.1.0.dist-info/WHEEL
json_memoize-1.1.0.dist-info/top_level.txt
json_memoize-1.1.0.dist-info/RECORD
