Metadata-Version: 2.1
Name: json-memoize
Version: 1.1.0
Summary: A tool for light-duty persistent memoization
Home-page: https://github.com/phildavis17/json_memoize
Author: Phil Davis
Author-email: phildavis17@gmail.com
License: UNKNOWN
Project-URL: Bug Tracker, https://github.com/phildavis17/json_memoize/issues
Platform: UNKNOWN
Classifier: Programming Language :: Python :: 3
Classifier: License :: OSI Approved :: MIT License
Classifier: Operating System :: OS Independent
Requires-Python: >=3.8
License-File: LICENSE
Requires-Dist: appdirs
